{"title":"MIME类型","uid":"7608810a314c552a7d790b7ee545ec15","slug":"MIME类型","date":"2020-03-09T08:03:50.000Z","updated":"2020-04-13T00:46:30.000Z","comments":true,"path":"api/articles/MIME类型.json","keywords":"A1andNS","cover":null,"content":"<p><strong>媒体类型</strong>（通常称为 <strong>Multipurpose Internet Mail Extensions</strong> 或 <strong>MIME</strong> 类型 ）是一种标准，用来表示文档、文件或字节流的性质和格式。<br>本文只为方便查询相应格式文件的MIME类型</p>\n<table>\n<thead>\n<tr>\n<th align=\"left\">扩展名</th>\n<th align=\"left\">文档类型</th>\n<th align=\"left\">MIME 类型</th>\n</tr>\n</thead>\n<tbody><tr>\n<td align=\"left\"><code>.aac</code></td>\n<td align=\"left\">AAC audio</td>\n<td align=\"left\"><code>audio/aac</code></td>\n</tr>\n<tr>\n<td align=\"left\"><code>.abw</code></td>\n<td align=\"left\"><a href=\"https://en.wikipedia.org/wiki/AbiWord\">AbiWord</a> document</td>\n<td align=\"left\"><code>application/x-abiword</code></td>\n</tr>\n<tr>\n<td align=\"left\"><code>.arc</code></td>\n<td align=\"left\">Archive document (multiple files embedded)</td>\n<td align=\"left\"><code>application/x-freearc</code></td>\n</tr>\n<tr>\n<td align=\"left\"><code>.avi</code></td>\n<td align=\"left\">AVI: Audio Video Interleave</td>\n<td align=\"left\"><code>video/x-msvideo</code></td>\n</tr>\n<tr>\n<td align=\"left\"><code>.azw</code></td>\n<td align=\"left\">Amazon Kindle eBook format</td>\n<td align=\"left\"><code>application/vnd.amazon.ebook</code></td>\n</tr>\n<tr>\n<td align=\"left\"><code>.bin</code></td>\n<td align=\"left\">Any kind of binary data</td>\n<td align=\"left\"><code>application/octet-stream</code></td>\n</tr>\n<tr>\n<td align=\"left\"><code>.bmp</code></td>\n<td align=\"left\">Windows OS/2 Bitmap Graphics</td>\n<td align=\"left\"><code>image/bmp</code></td>\n</tr>\n<tr>\n<td align=\"left\"><code>.bz</code></td>\n<td align=\"left\">BZip archive</td>\n<td align=\"left\"><code>application/x-bzip</code></td>\n</tr>\n<tr>\n<td align=\"left\"><code>.bz2</code></td>\n<td align=\"left\">BZip2 archive</td>\n<td align=\"left\"><code>application/x-bzip2</code></td>\n</tr>\n<tr>\n<td align=\"left\"><code>.csh</code></td>\n<td align=\"left\">C-Shell script</td>\n<td align=\"left\"><code>application/x-csh</code></td>\n</tr>\n<tr>\n<td align=\"left\"><code>.css</code></td>\n<td align=\"left\">Cascading Style Sheets (CSS)</td>\n<td align=\"left\"><code>text/css</code></td>\n</tr>\n<tr>\n<td align=\"left\"><code>.csv</code></td>\n<td align=\"left\">Comma-separated values (CSV)</td>\n<td align=\"left\"><code>text/csv</code></td>\n</tr>\n<tr>\n<td align=\"left\"><code>.doc</code></td>\n<td align=\"left\">Microsoft Word</td>\n<td align=\"left\"><code>application/msword</code></td>\n</tr>\n<tr>\n<td align=\"left\"><code>.docx</code></td>\n<td align=\"left\">Microsoft Word (OpenXML)</td>\n<td align=\"left\"><code>application/vnd.openxmlformats-officedocument.wordprocessingml.document</code></td>\n</tr>\n<tr>\n<td align=\"left\"><code>.eot</code></td>\n<td align=\"left\">MS Embedded OpenType fonts</td>\n<td align=\"left\"><code>application/vnd.ms-fontobject</code></td>\n</tr>\n<tr>\n<td align=\"left\"><code>.epub</code></td>\n<td align=\"left\">Electronic publication (EPUB)</td>\n<td align=\"left\"><code>application/epub+zip</code></td>\n</tr>\n<tr>\n<td align=\"left\"><code>.gif</code></td>\n<td align=\"left\">Graphics Interchange Format (GIF)</td>\n<td align=\"left\"><code>image/gif</code></td>\n</tr>\n<tr>\n<td align=\"left\"><code>.htm     .html</code></td>\n<td align=\"left\">HyperText Markup Language (HTML)</td>\n<td align=\"left\"><code>text/html</code></td>\n</tr>\n<tr>\n<td align=\"left\"><code>.ico</code></td>\n<td align=\"left\">Icon format</td>\n<td align=\"left\"><code>image/vnd.microsoft.icon</code></td>\n</tr>\n<tr>\n<td align=\"left\"><code>.ics</code></td>\n<td align=\"left\">iCalendar format</td>\n<td align=\"left\"><code>text/calendar</code></td>\n</tr>\n<tr>\n<td align=\"left\"><code>.jar</code></td>\n<td align=\"left\">Java Archive (JAR)</td>\n<td align=\"left\"><code>application/java-archive</code></td>\n</tr>\n<tr>\n<td align=\"left\"><code>.jpeg</code>      <code>.jpg</code></td>\n<td align=\"left\">JPEG images</td>\n<td align=\"left\"><code>image/jpeg</code></td>\n</tr>\n<tr>\n<td align=\"left\"><code>.js</code></td>\n<td align=\"left\">JavaScript</td>\n<td align=\"left\"><code>text/javascript</code></td>\n</tr>\n<tr>\n<td align=\"left\"><code>.json</code></td>\n<td align=\"left\">JSON format</td>\n<td align=\"left\"><code>application/json</code></td>\n</tr>\n<tr>\n<td align=\"left\"><code>.jsonld</code></td>\n<td align=\"left\">JSON-LD format</td>\n<td align=\"left\"><code>application/ld+json</code></td>\n</tr>\n<tr>\n<td align=\"left\"><code>.mid</code>      <code>.midi</code></td>\n<td align=\"left\">Musical Instrument Digital Interface (MIDI)</td>\n<td align=\"left\"><code>audio/midi</code> <code>audio/x-midi</code></td>\n</tr>\n<tr>\n<td align=\"left\"><code>.mjs</code></td>\n<td align=\"left\">JavaScript module</td>\n<td align=\"left\"><code>text/javascript</code></td>\n</tr>\n<tr>\n<td align=\"left\"><code>.mp3</code></td>\n<td align=\"left\">MP3 audio</td>\n<td align=\"left\"><code>audio/mpeg</code></td>\n</tr>\n<tr>\n<td align=\"left\"><code>.mpeg</code></td>\n<td align=\"left\">MPEG Video</td>\n<td align=\"left\"><code>video/mpeg</code></td>\n</tr>\n<tr>\n<td align=\"left\"><code>.mpkg</code></td>\n<td align=\"left\">Apple Installer Package</td>\n<td align=\"left\"><code>application/vnd.apple.installer+xml</code></td>\n</tr>\n<tr>\n<td align=\"left\"><code>.odp</code></td>\n<td align=\"left\">OpenDocument presentation document</td>\n<td align=\"left\"><code>application/vnd.oasis.opendocument.presentation</code></td>\n</tr>\n<tr>\n<td align=\"left\"><code>.ods</code></td>\n<td align=\"left\">OpenDocument spreadsheet document</td>\n<td align=\"left\"><code>application/vnd.oasis.opendocument.spreadsheet</code></td>\n</tr>\n<tr>\n<td align=\"left\"><code>.odt</code></td>\n<td align=\"left\">OpenDocument text document</td>\n<td align=\"left\"><code>application/vnd.oasis.opendocument.text</code></td>\n</tr>\n<tr>\n<td align=\"left\"><code>.oga</code></td>\n<td align=\"left\">OGG audio</td>\n<td align=\"left\"><code>audio/ogg</code></td>\n</tr>\n<tr>\n<td align=\"left\"><code>.ogv</code></td>\n<td align=\"left\">OGG video</td>\n<td align=\"left\"><code>video/ogg</code></td>\n</tr>\n<tr>\n<td align=\"left\"><code>.ogx</code></td>\n<td align=\"left\">OGG</td>\n<td align=\"left\"><code>application/ogg</code></td>\n</tr>\n<tr>\n<td align=\"left\"><code>.otf</code></td>\n<td align=\"left\">OpenType font</td>\n<td align=\"left\"><code>font/otf</code></td>\n</tr>\n<tr>\n<td align=\"left\"><code>.png</code></td>\n<td align=\"left\">Portable Network Graphics</td>\n<td align=\"left\"><code>image/png</code></td>\n</tr>\n<tr>\n<td align=\"left\"><code>.pdf</code></td>\n<td align=\"left\">Adobe <a href=\"https://acrobat.adobe.com/us/en/why-adobe/about-adobe-pdf.html\">Portable Document Format</a> (PDF)</td>\n<td align=\"left\"><code>application/pdf</code></td>\n</tr>\n<tr>\n<td align=\"left\"><code>.ppt</code></td>\n<td align=\"left\">Microsoft PowerPoint</td>\n<td align=\"left\"><code>application/vnd.ms-powerpoint</code></td>\n</tr>\n<tr>\n<td align=\"left\"><code>.pptx</code></td>\n<td align=\"left\">Microsoft PowerPoint (OpenXML)</td>\n<td align=\"left\"><code>application/vnd.openxmlformats-officedocument.presentationml.presentation</code></td>\n</tr>\n<tr>\n<td align=\"left\"><code>.rar</code></td>\n<td align=\"left\">RAR archive</td>\n<td align=\"left\"><code>application/x-rar-compressed</code></td>\n</tr>\n<tr>\n<td align=\"left\"><code>.rtf</code></td>\n<td align=\"left\">Rich Text Format (RTF)</td>\n<td align=\"left\"><code>application/rtf</code></td>\n</tr>\n<tr>\n<td align=\"left\"><code>.sh</code></td>\n<td align=\"left\">Bourne shell script</td>\n<td align=\"left\"><code>application/x-sh</code></td>\n</tr>\n<tr>\n<td align=\"left\"><code>.svg</code></td>\n<td align=\"left\">Scalable Vector Graphics (SVG)</td>\n<td align=\"left\"><code>image/svg+xml</code></td>\n</tr>\n<tr>\n<td align=\"left\"><code>.swf</code></td>\n<td align=\"left\"><a href=\"https://en.wikipedia.org/wiki/SWF\">Small web format</a> (SWF) or Adobe Flash document</td>\n<td align=\"left\"><code>application/x-shockwave-flash</code></td>\n</tr>\n<tr>\n<td align=\"left\"><code>.tar</code></td>\n<td align=\"left\">Tape Archive (TAR)</td>\n<td align=\"left\"><code>application/x-tar</code></td>\n</tr>\n<tr>\n<td align=\"left\"><code>.tif     .tiff</code></td>\n<td align=\"left\">Tagged Image File Format (TIFF)</td>\n<td align=\"left\"><code>image/tiff</code></td>\n</tr>\n<tr>\n<td align=\"left\"><code>.ttf</code></td>\n<td align=\"left\">TrueType Font</td>\n<td align=\"left\"><code>font/ttf</code></td>\n</tr>\n<tr>\n<td align=\"left\"><code>.txt</code></td>\n<td align=\"left\">Text, (generally ASCII or ISO 8859-<em>n</em>)</td>\n<td align=\"left\"><code>text/plain</code></td>\n</tr>\n<tr>\n<td align=\"left\"><code>.vsd</code></td>\n<td align=\"left\">Microsoft Visio</td>\n<td align=\"left\"><code>application/vnd.visio</code></td>\n</tr>\n<tr>\n<td align=\"left\"><code>.wav</code></td>\n<td align=\"left\">Waveform Audio Format</td>\n<td align=\"left\"><code>audio/wav</code></td>\n</tr>\n<tr>\n<td align=\"left\"><code>.weba</code></td>\n<td align=\"left\">WEBM audio</td>\n<td align=\"left\"><code>audio/webm</code></td>\n</tr>\n<tr>\n<td align=\"left\"><code>.webm</code></td>\n<td align=\"left\">WEBM video</td>\n<td align=\"left\"><code>video/webm</code></td>\n</tr>\n<tr>\n<td align=\"left\"><code>.webp</code></td>\n<td align=\"left\">WEBP image</td>\n<td align=\"left\"><code>image/webp</code></td>\n</tr>\n<tr>\n<td align=\"left\"><code>.woff</code></td>\n<td align=\"left\">Web Open Font Format (WOFF)</td>\n<td align=\"left\"><code>font/woff</code></td>\n</tr>\n<tr>\n<td align=\"left\"><code>.woff2</code></td>\n<td align=\"left\">Web Open Font Format (WOFF)</td>\n<td align=\"left\"><code>font/woff2</code></td>\n</tr>\n<tr>\n<td align=\"left\"><code>.xhtml</code></td>\n<td align=\"left\">XHTML</td>\n<td align=\"left\"><code>application/xhtml+xml</code></td>\n</tr>\n<tr>\n<td align=\"left\"><code>.xls</code></td>\n<td align=\"left\">Microsoft Excel</td>\n<td align=\"left\"><code>application/vnd.ms-excel</code></td>\n</tr>\n<tr>\n<td align=\"left\"><code>.xlsx</code></td>\n<td align=\"left\">Microsoft Excel (OpenXML)</td>\n<td align=\"left\"><code>application/vnd.openxmlformats-officedocument.spreadsheetml.sheet</code></td>\n</tr>\n<tr>\n<td align=\"left\"><code>.xml</code></td>\n<td align=\"left\"><code>XML</code></td>\n<td align=\"left\"><code>application/xml</code> 代码对普通用户来说不可读 (<a href=\"https://tools.ietf.org/html/rfc3023#section-3\">RFC 3023</a>, section 3)      <code>text/xml</code> 代码对普通用户来说可读 (<a href=\"https://tools.ietf.org/html/rfc3023#section-3\">RFC 3023</a>, section 3)</td>\n</tr>\n<tr>\n<td align=\"left\"><code>.xul</code></td>\n<td align=\"left\">XUL</td>\n<td align=\"left\"><code>application/vnd.mozilla.xul+xml</code></td>\n</tr>\n<tr>\n<td align=\"left\"><code>.zip</code></td>\n<td align=\"left\">ZIP archive</td>\n<td align=\"left\"><code>application/zip</code></td>\n</tr>\n<tr>\n<td align=\"left\"><code>.3gp</code></td>\n<td align=\"left\"><a href=\"https://en.wikipedia.org/wiki/3GP_and_3G2\">3GPP</a> audio/video container</td>\n<td align=\"left\"><code>video/3gpp</code>      <code>audio/3gpp</code>（若不含视频）</td>\n</tr>\n<tr>\n<td align=\"left\"><code>.3g2</code></td>\n<td align=\"left\"><a href=\"https://en.wikipedia.org/wiki/3GP_and_3G2\">3GPP2</a> audio/video container</td>\n<td align=\"left\"><code>video/3gpp2</code>      <code>audio/3gpp2</code>（若不含视频）</td>\n</tr>\n<tr>\n<td align=\"left\"><code>.7z</code></td>\n<td align=\"left\"><a href=\"https://en.wikipedia.org/wiki/7-Zip\">7-zip</a> archive</td>\n<td align=\"left\"><code>application/x-7z-compressed</code></td>\n</tr>\n</tbody></table>\n<p><strong>参考文献</strong><br>[1] <a href=\"https://developer.mozilla.org/zh-CN/docs/Web/HTTP/Basics_of_HTTP/MIME_Types\">https://developer.mozilla.org/zh-CN/docs/Web/HTTP/Basics_of_HTTP/MIME_Types</a><br>[2]<a href=\"https://developer.mozilla.org/zh-CN/docs/Web/HTTP/Basics_of_HTTP/MIME_types/Complete_list_of_MIME_types\">https://developer.mozilla.org/zh-CN/docs/Web/HTTP/Basics_of_HTTP/MIME_types/Complete_list_of_MIME_types</a><br>感谢MSD web docs对互联网事业的贡献</p>\n","text":"媒体类型（通常称为 Multipurpose Internet Mail Extensions 或 MIME 类型 ）是一种标准，用来表示文档、文件或字节流的性质和格式。本文只为方便查询相应格式文件的MIME类型 扩展名 文档类型 MIME 类型 .aac AAC audio a...","link":"","photos":[],"count_time":{"symbolsCount":"3.8k","symbolsTime":"3 mins."},"categories":[{"name":"学习笔记","slug":"学习笔记","count":35,"path":"api/categories/学习笔记.json"}],"tags":[{"name":"网络安全","slug":"网络安全","count":32,"path":"api/tags/网络安全.json"}],"toc":"","author":{"name":"A1andNS","slug":"blog-author","avatar":"/svg/head.png","link":"/","description":"爱你所爱，行你所行，听从你心，无问西东","socials":{"github":"https://github.com/A1andNS","twitter":"","stackoverflow":"","wechat":"","qq":"","weibo":"","zhihu":"","csdn":"","juejin":"","customs":{}}},"mapped":true,"prev_post":{"title":"Hackinglab基础关Write Up","uid":"2e3b9c7b91bc48ac2226d050fa8b2439","slug":"Hackinglab基础关Write-Up","date":"2020-03-09T08:04:44.000Z","updated":"2020-10-02T10:14:26.000Z","comments":true,"path":"api/articles/Hackinglab基础关Write-Up.json","keywords":"A1andNS","cover":[],"text":"第一题：key在哪里？打开目标网站，按他的提示就在这里，查看网页源代码就得到了key is jflsjklejflkdsjfklds 第二题：再加密一次你就的到key根据提示我们知道了明文加密一次后是密文，再加密一次又可以得到明文，故判定是rot13加密的，我使用了CTFCrak...","link":"","photos":[],"count_time":{"symbolsCount":"3.1k","symbolsTime":"3 mins."},"categories":[{"name":"CTF","slug":"CTF","count":43,"path":"api/categories/CTF.json"}],"tags":[{"name":"网络安全","slug":"网络安全","count":32,"path":"api/tags/网络安全.json"},{"name":"WEB","slug":"WEB","count":39,"path":"api/tags/WEB.json"}],"author":{"name":"A1andNS","slug":"blog-author","avatar":"/svg/head.png","link":"/","description":"爱你所爱，行你所行，听从你心，无问西东","socials":{"github":"https://github.com/A1andNS","twitter":"","stackoverflow":"","wechat":"","qq":"","weibo":"","zhihu":"","csdn":"","juejin":"","customs":{}}}},"next_post":{"title":"HTTP头文件（持续更新）","uid":"fa89043ea17343f99a80dd6e1c6c7c73","slug":"HTTP头文件（持续更新）","date":"2020-03-09T08:03:01.000Z","updated":"2020-04-13T00:46:32.000Z","comments":true,"path":"api/articles/HTTP头文件（持续更新）.json","keywords":"A1andNS","cover":[],"text":"HTTP头文件简介（持续更新）HTTP头文件可以包含很多有用的信息，但作为初学者大多数是不清楚这些内容的含义和作用，故我在学习过程中记录下主要的头文件内容的含义和作用，以备后续考查。本文会不定期持续更新。。。。。。 请求头下图为火狐浏览器的火狐主页https://home.fir...","link":"","photos":[],"count_time":{"symbolsCount":"2.7k","symbolsTime":"2 mins."},"categories":[{"name":"学习笔记","slug":"学习笔记","count":35,"path":"api/categories/学习笔记.json"}],"tags":[{"name":"网络安全","slug":"网络安全","count":32,"path":"api/tags/网络安全.json"},{"name":"WEB","slug":"WEB","count":39,"path":"api/tags/WEB.json"}],"author":{"name":"A1andNS","slug":"blog-author","avatar":"/svg/head.png","link":"/","description":"爱你所爱，行你所行，听从你心，无问西东","socials":{"github":"https://github.com/A1andNS","twitter":"","stackoverflow":"","wechat":"","qq":"","weibo":"","zhihu":"","csdn":"","juejin":"","customs":{}}}}}